pybanq/__init__.py
pybanq/asi/__init__.py
pybanq/asi/data_science.py
pybanq/asi/deepRL/.DS_Store
pybanq/asi/deepRL/.gitignore
pybanq/asi/deepRL/__init__.py
pybanq/asi/deepRL/agent.py
pybanq/asi/deepRL/config.py
pybanq/asi/deepRL/funcs.py
pybanq/asi/deepRL/game.py
pybanq/asi/deepRL/games/.DS_Store
pybanq/asi/deepRL/games/__init__.py
pybanq/asi/deepRL/games/connect4/.DS_Store
pybanq/asi/deepRL/games/connect4/__init__.py
pybanq/asi/deepRL/games/connect4/game.py
pybanq/asi/deepRL/games/metasquares/.DS_Store
pybanq/asi/deepRL/games/metasquares/__init__.py
pybanq/asi/deepRL/games/metasquares/game.py
pybanq/asi/deepRL/initialise.py
pybanq/asi/deepRL/LICENSE
pybanq/asi/deepRL/loggers.py
pybanq/asi/deepRL/loss.py
pybanq/asi/deepRL/main.py
pybanq/asi/deepRL/MCTS.py
pybanq/asi/deepRL/memory.py
pybanq/asi/deepRL/model.py
pybanq/asi/deepRL/README.md
pybanq/asi/deepRL/requirements.txt
pybanq/asi/deepRL/run/.DS_Store
pybanq/asi/deepRL/run/__init__.py
pybanq/asi/deepRL/run/config.py
pybanq/asi/deepRL/run/logs/.DS_Store
pybanq/asi/deepRL/run/logs/.gitignore
pybanq/asi/deepRL/run/logs/__init__.py
pybanq/asi/deepRL/run/memory/.DS_Store
pybanq/asi/deepRL/run/memory/.gitignore
pybanq/asi/deepRL/run/memory/__init__.py
pybanq/asi/deepRL/run/models/.DS_Store
pybanq/asi/deepRL/run/models/.gitignore
pybanq/asi/deepRL/run/models/__init__.py
pybanq/asi/deepRL/run.ipynb
pybanq/asi/deepRL/settings.py
pybanq/asi/deepRL/utils.py
pybanq/asi/extract.py
pybanq/asi/gan.py
pybanq/asi/gaussian_mixtures.py
pybanq/asi/nlp.py
pybanq/block/__init__.py
pybanq/nano/__init__.py
pybanq/quantum/__init__.py
pybanq-0.1.1.dist-info/WHEEL
pybanq-0.1.1.dist-info/METADATA
pybanq-0.1.1.dist-info/RECORD
