Metadata-Version: 2.1
Name: pybanq
Version: 0.1.1
Summary: 
Author: Jachiike Madubuko
Author-email: jachiike.madubuko@gmail.com
Requires-Python: >=3.7,<4.0
Classifier: Programming Language :: Python :: 3
Classifier: Programming Language :: Python :: 3.7
Classifier: Programming Language :: Python :: 3.8
Requires-Dist: keras (>=2.3.1,<3.0.0)
Requires-Dist: matplotlib (>=3.2.1,<4.0.0)
Requires-Dist: nltk (>=3.5,<4.0)
Requires-Dist: scipy (>=1.4.1,<2.0.0)
Requires-Dist: seaborn (>=0.10.1,<0.11.0)
Requires-Dist: tqdm (>=4.46.0,<5.0.0)
